requests_onshape/__init__.py
requests_onshape-0.0.1.dist-info/METADATA
requests_onshape-0.0.1.dist-info/RECORD
requests_onshape-0.0.1.dist-info/WHEEL
requests_onshape-0.0.1.dist-info/top_level.txt
