Metadata-Version: 2.1
Name: requests-onshape
Version: 0.0.1
Summary: UNKNOWN
Home-page: https://github.com/ovidner/requests-onshape
Author: Olle Vidner
Author-email: olle@vidner.se
License: MIT
Platform: UNKNOWN
Requires-Dist: requests
